graiax_sayamod_nbnhhsh/__init__.py
graiax_sayamod_nbnhhsh-0.1.6.dist-info/LICENSE
graiax_sayamod_nbnhhsh-0.1.6.dist-info/WHEEL
graiax_sayamod_nbnhhsh-0.1.6.dist-info/METADATA
graiax_sayamod_nbnhhsh-0.1.6.dist-info/RECORD
