Metadata-Version: 2.1
Name: graiax-sayamod-nbnhhsh
Version: 0.1.6
Summary: [Saya模块]能不能好好说话——缩写查询
License: AGPL 3.0
Author: Eric
Author-email: erictianc@outlook.com
Requires-Python: >=3.8,<4.0
Classifier: License :: Other/Proprietary License
Classifier: Programming Language :: Python :: 3
Classifier: Programming Language :: Python :: 3.8
Classifier: Programming Language :: Python :: 3.9
Requires-Dist: aiosonic (>=0.9.5,<0.10.0)
Requires-Dist: graia-application-mirai (>=0.16.1,<0.17.0)
Requires-Dist: graia-saya (>=0.0.8,<0.0.9)
